LICENSE.txt
MANIFEST.in
README.rst
setup.cfg
setup.py
Phils_Amazon_Price_Tracker.egg-info/PKG-INFO
Phils_Amazon_Price_Tracker.egg-info/SOURCES.txt
Phils_Amazon_Price_Tracker.egg-info/dependency_links.txt
Phils_Amazon_Price_Tracker.egg-info/entry_points.txt
Phils_Amazon_Price_Tracker.egg-info/requires.txt
Phils_Amazon_Price_Tracker.egg-info/top_level.txt
data/data_file
priceTracker/__init__.py
priceTracker/__main__.py
priceTracker/graph.py
priceTracker/outputChange.py
priceTracker/priceTrackerClass.py
priceTracker/product.py
priceTracker/save_data.py
priceTracker/analyse/__init__.py
priceTracker/analyse/amazon.py