Metadata-Version: 1.1
Name: Phils-Amazon-Price-Tracker
Version: 1.2.0.dev1
Summary: An Amazon Product Price Tracker
Home-page: https://github.com/pypa/sampleproject
Author: Phil H
Author-email: philipp.haeusele@gmail.com
License: MIT
Keywords: amzon product price tracker
Platform: UNKNOWN
Classifier: Development Status :: 4 - Beta
Classifier: Intended Audience :: Developers
Classifier: Topic :: Internet :: WWW/HTTP :: Indexing/Search
Classifier: License :: OSI Approved :: MIT License
Classifier: Programming Language :: Python :: 3.3
Classifier: Programming Language :: Python :: 3.4
Classifier: Programming Language :: Python :: 3.5
